hitchskeleton/__init__.py
hitchskeleton/app.py
hitchskeleton/template.py
hitchskeleton-0.1.2.dist-info/LICENSE
hitchskeleton-0.1.2.dist-info/METADATA
hitchskeleton-0.1.2.dist-info/WHEEL
hitchskeleton-0.1.2.dist-info/entry_points.txt
hitchskeleton-0.1.2.dist-info/top_level.txt
hitchskeleton-0.1.2.dist-info/RECORD
