Metadata-Version: 2.1
Name: hitchskeleton
Version: 0.1.2
Summary: Bootstrap an integration test environment.
Author-email: Colm O'Connor <colm.oconnor.github@gmail.com>
License: MIT
Project-URL: homepage, https://hitchdev.com/hitchskeleton
Project-URL: documentation, https://hitchdev.com/hitchskeleton/using
Project-URL: repository, https://github.com/hitchdev/hitchskeleton
Project-URL: changelog, https://hitchdev.com/hitchskeleton/changelog
Keywords: integration-tests,tests,testing,jinja2
Classifier: Programming Language :: Python :: 3
Classifier: License :: OSI Approved :: MIT License
Classifier: Topic :: Text Processing :: Markup
Classifier: Topic :: Software Development :: Libraries
Classifier: Natural Language :: English
Requires-Python: >=3.7.0
License-File: LICENSE
Requires-Dist: click >=8.1.3
Requires-Dist: commandlib >=0.3.5
Requires-Dist: path.py >12.0
